{"id":1255,"cast":[{"cast_id":3,"character":"Park Gang-du","credit_id":"52fe42eac3a36847f802ca31","gender":2,"id":20738,"name":"Song Kang-ho","order":0,"profile_path":"/joAXWwyjeed7qRDJ6jxSiMi7f5i.jpg"},{"cast_id":15,"character":"Park Hie-bong","credit_id":"56169cd49251410d80012453","gender":2,"id":116180,"name":"Byun Hee-bong","order":1,"profile_path":"/k4Vip2LOUaM0Xdk5cxqVOojhxZe.jpg"},{"cast_id":5,"character":"Park Nam-il","credit_id":"52fe42eac3a36847f802ca39","gender":2,"id":21687,"name":"Park Hae-il","order":2,"profile_path":"/j5hBeocw5nttNt690QnsbgwgxSS.jpg"},{"cast_id":6,"character":"Park Nam-joo","credit_id":"52fe42eac3a36847f802ca3d","gender":1,"id":21688,"name":"Bae Doo-na","order":3,"profile_path":"/owMv65TuU4thBBJCpv3uWr1bWfc.jpg"},{"cast_id":7,"character":"Park Hyun-seo","credit_id":"52fe42eac3a36847f802ca41","gender":1,"id":21689,"name":"Go Ah-sung","order":4,"profile_path":"/ypLzFARDiB0S8eV8YWj0mi5vmJW.jpg"},{"cast_id":21,"character":"The Monster (Voice)","credit_id":"5a3c0a87c3a368148f09bb9b","gender":2,"id":77188,"name":"Oh Dal-su","order":5,"profile_path":"/5DmhRuUQZlrjoaN6seg7Wut3elb.jpg"},{"cast_id":22,"character":"Se-jin","credit_id":"5a3c0a9d0e0a264cbe224e50","gender":2,"id":1307736,"name":"Lee Jae-eung","order":6,"profile_path":"/nmO1DtyP0vge68rIqQAGhtgDSUW.jpg"},{"cast_id":23,"character":"Se-joo","credit_id":"5a3c0abcc3a3680b8d229129","gender":0,"id":1180191,"name":"Lee Dong-ho","order":7,"profile_path":null},{"cast_id":24,"character":"Homeless Man","credit_id":"5a3c0acdc3a36814ab0ae699","gender":2,"id":141541,"name":"Yoon Je-moon","order":8,"profile_path":"/3IIcZsGsgwv1hqsyGx2rx8JNPOA.jpg"},{"cast_id":26,"character":"Yellow 1","credit_id":"5a3c0af4c3a36814ab0ae6dd","gender":0,"id":1946019,"name":"Kim Roi-ha","order":9,"profile_path":null},{"cast_id":31,"character":"Inquiry Officer","credit_id":"5a668cab92514169be001914","gender":0,"id":1311982,"name":"Park No-sik","order":10,"profile_path":null},{"cast_id":35,"character":"Hostage Nurse","credit_id":"5b92b61a0e0a2679b400283b","gender":1,"id":1190229,"name":"Koh Soo-hee","order":11,"profile_path":"/mhQWl9wQuuNPcHqiojbtLNrBTge.jpg"},{"cast_id":25,"character":"\"Fat Guevara\"","credit_id":"5a3c0ae60e0a264cbe224ed0","gender":2,"id":94003,"name":"Yim Pil-sung","order":12,"profile_path":"/rt1wX2hK4iDwYgF02Cqv8YeFTSB.jpg"},{"cast_id":29,"character":"Donald","credit_id":"5a3c0b510e0a264cd022d870","gender":0,"id":79580,"name":"David Anselmo","order":13,"profile_path":null},{"cast_id":18,"character":"American Doctor","credit_id":"5776a94592514174d2001e5d","gender":2,"id":6914,"name":"Scott Wilson","order":14,"profile_path":"/uAPQD3zXThKHXaYELx3ePSzeWwM.jpg"},{"cast_id":20,"character":"US Doctor trying to operate Gang-Du","credit_id":"5956a8fbc3a3680d73061d61","gender":2,"id":138988,"name":"Paul Lazar","order":15,"profile_path":"/tYql2muBX2aJpUtteoRmPSLcJTl.jpg"},{"cast_id":30,"character":"Young Korean Doctor","credit_id":"5a3c0bb80e0a264cc122505d","gender":0,"id":1946027,"name":"Brian Lee","order":16,"profile_path":null},{"cast_id":32,"character":"City Ward Division Director","credit_id":"5a9dc793c3a368428e005b51","gender":2,"id":138542,"name":"Yoo Yeon-soo","order":17,"profile_path":null},{"cast_id":33,"character":"Weeping Woman","credit_id":"5aa0d1f70e0a2644da0010a4","gender":1,"id":1887008,"name":"Kim Choo-wol","order":18,"profile_path":null},{"cast_id":34,"character":"Couple man","credit_id":"5b7a4abe0e0a264731039b5b","gender":2,"id":2104478,"name":"Lee Eung-jae","order":19,"profile_path":null},{"cast_id":37,"character":"Girl's Father","credit_id":"5bb2b00a92514142660015f1","gender":2,"id":1291106,"name":"Lee Seung-jin","order":20,"profile_path":null},{"cast_id":42,"character":"Phone camera girl","credit_id":"5cee6e639251411943b8f5de","gender":1,"id":2119921,"name":"Moon Hee-ra","order":21,"profile_path":null},{"cast_id":43,"character":"Taxi driver","credit_id":"5d264dc9a698cf0f59a6df28","gender":2,"id":1128004,"name":"Yoo Seung-mok","order":22,"profile_path":"/ljbvYvl7Kxj6WMWq48pslnXwsML.jpg"}],"crew":[{"credit_id":"52fe42eac3a36847f802ca27","department":"Directing","gender":2,"id":21684,"job":"Director","name":"Bong Joon-ho","profile_path":"/stwnTvZAoD8gEJEDHpDQyLCyDy5.jpg"},{"credit_id":"52fe42eac3a36847f802ca2d","department":"Writing","gender":0,"id":21685,"job":"Screenplay","name":"Chul-hyun Baek","profile_path":null},{"credit_id":"52fe42eac3a36847f802ca47","department":"Writing","gender":2,"id":21684,"job":"Screenplay","name":"Bong Joon-ho","profile_path":"/stwnTvZAoD8gEJEDHpDQyLCyDy5.jpg"},{"credit_id":"52fe42eac3a36847f802ca4d","department":"Production","gender":2,"id":16281,"job":"Producer","name":"Choi Yong-bae","profile_path":null},{"credit_id":"52fe42eac3a36847f802ca53","department":"Sound","gender":2,"id":21690,"job":"Original Music Composer","name":"Lee Byung-woo","profile_path":null},{"credit_id":"52fe42eac3a36847f802ca59","department":"Camera","gender":2,"id":17133,"job":"Director of Photography","name":"Kim Hyung-koo","profile_path":"/kw01vO74mPLlwIDnVNOqCIcCrsB.jpg"},{"credit_id":"52fe42eac3a36847f802ca6b","department":"Art","gender":1,"id":10109,"job":"Production Design","name":"Ryu Seong-hee","profile_path":"/u7HVjLQiCuia9TwsGefkH2QyJRS.jpg"},{"credit_id":"568f0167c3a36858f9003f5b","department":"Production","gender":0,"id":1531380,"job":"Producer","name":"Junyoung Jang","profile_path":null},{"credit_id":"56394955c3a3681b5e01f343","department":"Production","gender":0,"id":1531380,"job":"Co-Producer","name":"Junyoung Jang","profile_path":null},{"credit_id":"590264e8c3a36840be00431d","department":"Editing","gender":0,"id":69388,"job":"Editor","name":"Kim Sun-min","profile_path":null},{"credit_id":"5ba8e9a30e0a2635dd04b132","department":"Visual Effects","gender":1,"id":1142301,"job":"Visual Effects Coordinator","name":"Karen Kelly","profile_path":null},{"credit_id":"5c10694592514147950e4a90","department":"Costume & Make-Up","gender":1,"id":43570,"job":"Costume Design","name":"Cho Sang-kyung","profile_path":"/aTd5Tq5P6a41Q4kYRn9yxuj8xy8.jpg"},{"credit_id":"5c2db4ae9251416d946bbcd5","department":"Camera","gender":2,"id":1293085,"job":"Camera Operator","name":"Kim Byung-seo","profile_path":"/pTLt6yd4khAUwgUf0D0P1DBTBHe.jpg"},{"credit_id":"5c358e71925141576f6d6af5","department":"Sound","gender":2,"id":10110,"job":"Recording Supervision","name":"Lee Seung-chul","profile_path":null},{"credit_id":"5cd7e00f9251415ec5cd7f84","department":"Costume & Make-Up","gender":0,"id":2078588,"job":"Makeup & Hair","name":"Song Jong-hee","profile_path":null},{"credit_id":"5d4be1a9002134001327a24a","department":"Art","gender":2,"id":1981616,"job":"Set Decoration","name":"Yang Hong-sam","profile_path":null}]}