{"id":1640,"cast":[{"cast_id":3,"character":"Jean Cabot","credit_id":"52fe4307c3a36847f803503d","gender":1,"id":18277,"name":"Sandra Bullock","order":0,"profile_path":"/h14DpolXksHdpHF18ubtqslvorO.jpg"},{"cast_id":4,"character":"Det. Graham Waters","credit_id":"52fe4307c3a36847f8035041","gender":2,"id":1896,"name":"Don Cheadle","order":1,"profile_path":"/b1EVJWdFn7a75qVYJgwO87W2TJU.jpg"},{"cast_id":8,"character":"Officer John Ryan","credit_id":"52fe4307c3a36847f8035049","gender":2,"id":2876,"name":"Matt Dillon","order":2,"profile_path":"/wVoSUexYH79igPgxIXKWRlV2uBk.jpg"},{"cast_id":7,"character":"Daniel","credit_id":"52fe4307c3a36847f8035045","gender":2,"id":454,"name":"Michael Peña","order":3,"profile_path":"/oqlIKSglghuX7kSTalODn71nlOd.jpg"},{"cast_id":10,"character":"Ria","credit_id":"52fe4307c3a36847f803504d","gender":1,"id":18285,"name":"Jennifer Esposito","order":4,"profile_path":"/3AgSasBNdaUllSmmn2mc5K83SK3.jpg"},{"cast_id":11,"character":"Rick Cabot","credit_id":"52fe4307c3a36847f8035051","gender":2,"id":18269,"name":"Brendan Fraser","order":5,"profile_path":"/n8VOWXp94nhIEo5nS9o6bOpUHiN.jpg"},{"cast_id":12,"character":"Karen","credit_id":"52fe4307c3a36847f8035055","gender":1,"id":18286,"name":"Nona Gaye","order":6,"profile_path":"/2g6BDp6dUB6ql5xKEhY07IhxGkc.jpg"},{"cast_id":14,"character":"Cameron Thayer","credit_id":"52fe4307c3a36847f8035059","gender":2,"id":18288,"name":"Terrence Howard","order":7,"profile_path":"/MZeLxOH0PgL7xcvt865WVBvQDw.jpg"},{"cast_id":15,"character":"Anthony","credit_id":"52fe4307c3a36847f803505d","gender":2,"id":8171,"name":"Ludacris","order":8,"profile_path":"/xLfq9wFO6dtYuUK96hbJ8I8EKFw.jpg"},{"cast_id":16,"character":"Christine Thayer","credit_id":"52fe4307c3a36847f8035061","gender":1,"id":9030,"name":"Thandie Newton","order":9,"profile_path":"/sW6XsnM2DkX6ujOXZ38aIQAMIWi.jpg"},{"cast_id":18,"character":"Lara","credit_id":"52fe4307c3a36847f8035065","gender":1,"id":18290,"name":"Ashlyn Sanchez","order":10,"profile_path":"/flE8FT2vKQDCHp1C3sTB17bZQEg.jpg"},{"cast_id":19,"character":"Shereen","credit_id":"52fe4307c3a36847f8035069","gender":1,"id":2393,"name":"Marina Sirtis","order":11,"profile_path":"/ueHzqv6uN6Mhf1DC3IjTPhNafYq.jpg"},{"cast_id":20,"character":"Peter Waters","credit_id":"52fe4307c3a36847f803506d","gender":2,"id":18291,"name":"Larenz Tate","order":12,"profile_path":"/ApN0l0NF1fUp61PwffW09ZqEUMW.jpg"},{"cast_id":21,"character":"Graham's Mother","credit_id":"52fe4307c3a36847f8035071","gender":1,"id":18292,"name":"Beverly Todd","order":13,"profile_path":"/pu3WvCEFahtHXElYVwqgzo9x1p5.jpg"},{"cast_id":23,"character":"Officer Johnson","credit_id":"52fe4307c3a36847f8035075","gender":1,"id":18293,"name":"Kathleen York","order":14,"profile_path":"/9tpL5j3Ba6yewjIwohTQxZtt1gM.jpg"},{"cast_id":29,"character":"Lt. Dixon","credit_id":"52fe4307c3a36847f8035079","gender":2,"id":65827,"name":"Keith David","order":15,"profile_path":"/nwAC9TgwRkj0Ritq93O8GeublyL.jpg"},{"cast_id":32,"character":"Flanagan","credit_id":"52fe4307c3a36847f803507d","gender":2,"id":886,"name":"William Fichtner","order":16,"profile_path":"/apj1bgzZI2efSdJolfp6KjhG8CF.jpg"},{"cast_id":36,"character":"Park","credit_id":"52fe4307c3a36847f8035081","gender":2,"id":18307,"name":"Daniel Dae Kim","order":17,"profile_path":"/dehGaLoF7eq31pX0YXIS8KWGwv0.jpg"},{"cast_id":37,"character":"Officer Tom Hansen","credit_id":"52fe4307c3a36847f8035085","gender":2,"id":11864,"name":"Ryan Phillippe","order":18,"profile_path":"/8MlC0rqhMpDxnfFjmw2DKOhdVpB.jpg"},{"cast_id":43,"character":"Elizabeth","credit_id":"53a1c0940e0a266ff7000207","gender":1,"id":18282,"name":"Karina Arroyave","order":19,"profile_path":"/ngp9TbneTzhoHnBpgWhnhwb4L8u.jpg"},{"cast_id":44,"character":"Lucien","credit_id":"53a1c0bc0e0a266fe60001ff","gender":2,"id":18283,"name":"Dato Bakhtadze","order":20,"profile_path":"/1iittoHHIZtIalNt3DYsDu86FwL.jpg"},{"cast_id":45,"character":"Ken Ho","credit_id":"53a1c0e60e0a266ffa000218","gender":2,"id":18296,"name":"Art Chudabala","order":21,"profile_path":"/9Bs1cSvRpqYAFbzpGWvOeyoliaK.jpg"},{"cast_id":47,"character":"Fred","credit_id":"53a1c1440e0a266fe6000210","gender":2,"id":18298,"name":"Tony Danza","order":23,"profile_path":"/zuGqT0ZJQFm0GMUnEa32jYu75Fy.jpg"},{"cast_id":48,"character":"Shaniqua Johnson","credit_id":"53a1c1740e0a266ffa00022e","gender":1,"id":18284,"name":"Loretta Devine","order":24,"profile_path":"/9d5N0l3ylagkFZCc8pt743GfFZv.jpg"},{"cast_id":49,"character":"Georgie","credit_id":"53a1c1a60e0a266ff7000244","gender":2,"id":18299,"name":"Ime Etuk","order":25,"profile_path":null},{"cast_id":50,"character":"Officer Gomez","credit_id":"53a1c1d20e0a266ff3000202","gender":2,"id":18300,"name":"Eddie J. Fernandez","order":26,"profile_path":"/wzEilQWiKBsIJvn6vb3JzUvKU14.jpg"},{"cast_id":52,"character":"Store Owner","credit_id":"53a1c2160e0a266ffa00024f","gender":0,"id":18303,"name":"Howard Fong","order":28,"profile_path":null},{"cast_id":53,"character":"Officer Hill","credit_id":"53a1c23e0e0a266ffe000240","gender":2,"id":18304,"name":"Billy Gallo","order":29,"profile_path":null},{"cast_id":54,"character":"Bruce","credit_id":"53a1c2600e0a266ff3000212","gender":2,"id":18287,"name":"Ken Garito","order":30,"profile_path":"/eoAwE3UyWJNHrrChqv2x7WSkJIq.jpg"},{"cast_id":55,"character":"Hispanic Passenger","credit_id":"53a1c2870e0a266fec000271","gender":0,"id":130732,"name":"Octavio Gómez Berríos","order":31,"profile_path":null},{"cast_id":56,"character":"Lara's Friend","credit_id":"53a1c2a50e0a266ff300021d","gender":0,"id":1331790,"name":"James Haggis","order":32,"profile_path":null},{"cast_id":57,"character":"Nurse Hodges","credit_id":"53a1c2cd0e0a266ff3000224","gender":1,"id":61830,"name":"Sylva Kelegian","order":33,"profile_path":"/iY60KVSUGrItgKCMsJqarczgzqU.jpg"},{"cast_id":59,"character":"Security Guard","credit_id":"53a1c32e0e0a266ff3000229","gender":2,"id":154932,"name":"Jayden Lund","order":35,"profile_path":"/b0Ik6EB7HO7ZXKg9xdm8zvmBBWj.jpg"},{"cast_id":60,"character":"Gun Store Owner","credit_id":"53a1c34f0e0a266ff700027f","gender":2,"id":10489,"name":"Jack McGee","order":36,"profile_path":"/jSl2RKRaJvtRoS3T5HSw4xeNdwy.jpg"},{"cast_id":61,"character":"First Assistant Director","credit_id":"53a1c36a0e0a266fef000275","gender":1,"id":1110185,"name":"Amanda Moresco","order":37,"profile_path":null},{"cast_id":62,"character":"Conklin","credit_id":"53a1c39b0e0a266ff7000290","gender":0,"id":1331791,"name":"Martin Norseman","order":38,"profile_path":null},{"cast_id":63,"character":"Hispanic Driver","credit_id":"53a1c3b80e0a266fec000295","gender":2,"id":1331792,"name":"Joe Ordaz","order":39,"profile_path":"/wEdRYG6nkLPvTxoGEugHBLgpaKV.jpg"},{"cast_id":64,"character":"Choi","credit_id":"53a1c3d60e0a266ffe000270","gender":0,"id":191198,"name":"Greg Joung Paik","order":40,"profile_path":"/n3jIHCx5LAbfAVZfOW4WMxjKKui.jpg"},{"cast_id":65,"character":"Maria","credit_id":"53a1c4000e0a266fe600026e","gender":0,"id":18289,"name":"Yomi Perry","order":41,"profile_path":null},{"cast_id":66,"character":"Kim Lee","credit_id":"53a1c43e0e0a266fec0002aa","gender":0,"id":58930,"name":"Alexis Rhee","order":42,"profile_path":"/vu4RAoiD4eXXt0KRA882IwmZQAE.jpg"},{"cast_id":67,"character":"Woman at Locksmith's","credit_id":"53a1c4690e0a266fec0002b1","gender":0,"id":1331793,"name":"Molly Schaffer","order":43,"profile_path":null},{"cast_id":68,"character":"Officer Stone","credit_id":"53a1c4950e0a266ff3000266","gender":2,"id":1331794,"name":"Paul E. Short","order":44,"profile_path":"/1OV3dXnfssU9sgAlJL4x7rUoiSz.jpg"},{"cast_id":69,"character":"Dorri","credit_id":"53a1c4c00e0a266ffe00028e","gender":1,"id":2677,"name":"Bahar Soomekh","order":45,"profile_path":"/zUSvkgoCYyvLAoX8a9uWAqjuvBT.jpg"},{"cast_id":70,"character":"Paramedic","credit_id":"53a1c4dc0e0a266fe600028b","gender":2,"id":1331795,"name":"Allan Steele","order":46,"profile_path":"/tEEMzrtAJEDOoWhnoPCWLUq75aM.jpg"},{"cast_id":71,"character":"Receptionist","credit_id":"53a1c4f40e0a266fec0002c6","gender":0,"id":1331796,"name":"Kate Super","order":47,"profile_path":null},{"cast_id":72,"character":"Country DJ (voice)","credit_id":"53a1c51e0e0a266ff70002ce","gender":2,"id":18305,"name":"Glenn Taranto","order":48,"profile_path":"/kZfmHgAOYHprU9Iq30W7oTx9M7Y.jpg"},{"cast_id":73,"character":"Farhad","credit_id":"53a1c5490e0a266fe600029f","gender":2,"id":17857,"name":"Shaun Toub","order":49,"profile_path":"/qRHZD8EdqeUor8A6tazJ3v3gxyD.jpg"},{"cast_id":74,"character":"Carjack Witness (uncredited)","credit_id":"53a1c5780e0a266fec0002df","gender":2,"id":1263449,"name":"Curt Clendenin","order":50,"profile_path":"/uaH8jRUoOW1jwgz6q6WFlBJVmiB.jpg"},{"cast_id":75,"character":"Young Peter (uncredited)","credit_id":"53a1c5950e0a266ff70002d8","gender":0,"id":1331797,"name":"Alastair Douglas","order":51,"profile_path":null},{"cast_id":76,"character":"Jamal (uncredited)","credit_id":"53a1c5b00e0a266ff300028d","gender":2,"id":1331798,"name":"Nicholas George Stark","order":52,"profile_path":null},{"cast_id":77,"character":"Pop Ryan","credit_id":"55127c71c3a3686161000f3a","gender":0,"id":3042,"name":"Bruce Kirby","order":53,"profile_path":"/3QILwSvbhHBBR43MxskV0rm8p4i.jpg"},{"cast_id":113,"character":"Motorcycle Cop","credit_id":"577a7c2dc3a368770700084d","gender":2,"id":18297,"name":"Sean Cory Cooper","order":54,"profile_path":"/A27O4ajo6NVa5lJjGGX8ZiBa21I.jpg"}],"crew":[{"credit_id":"52fe4307c3a36847f8035033","department":"Directing","gender":2,"id":455,"job":"Director","name":"Paul Haggis","profile_path":"/v2MadHJVrBAv0tEgs9H9PJ9y50z.jpg"},{"credit_id":"52fe4307c3a36847f8035039","department":"Writing","gender":2,"id":455,"job":"Screenplay","name":"Paul Haggis","profile_path":"/v2MadHJVrBAv0tEgs9H9PJ9y50z.jpg"},{"credit_id":"52fe4307c3a36847f803508b","department":"Sound","gender":2,"id":4140,"job":"Original Music Composer","name":"Mark Isham","profile_path":"/juP82LbS9chU3VXgelb7CICBN2Q.jpg"},{"credit_id":"52fe4307c3a36847f8035091","department":"Editing","gender":2,"id":20649,"job":"Editor","name":"Hughes Winborne","profile_path":"/nIIkXDETAlS6UMPTqjCs4kRgAo4.jpg"},{"credit_id":"53a1c0350e0a266fec0001fc","department":"Camera","gender":2,"id":21118,"job":"Director of Photography","name":"James M. Muro","profile_path":null},{"credit_id":"558b708292514141d8001de1","department":"Writing","gender":2,"id":137064,"job":"Screenplay","name":"Robert Moresco","profile_path":null},{"credit_id":"5675cabec3a368167c003925","department":"Production","gender":1,"id":7232,"job":"Casting","name":"Sarah Finn","profile_path":null},{"credit_id":"5675cae092514179e3003673","department":"Production","gender":1,"id":20540,"job":"Casting","name":"Randi Hiller","profile_path":null},{"credit_id":"5675cafe92514179e7003688","department":"Directing","gender":0,"id":1458216,"job":"Script Supervisor","name":"Jay Mason","profile_path":null},{"credit_id":"5675cb1492514179dd003586","department":"Camera","gender":1,"id":589974,"job":"Still Photographer","name":"Lorey Sebastian","profile_path":null},{"credit_id":"5675cb28c3a368167c00392f","department":"Camera","gender":2,"id":1551221,"job":"Still Photographer","name":"Jim Sheldon","profile_path":null},{"credit_id":"5675cb6a92514179d20038ed","department":"Production","gender":2,"id":4232,"job":"Producer","name":"Bob Yari","profile_path":null},{"credit_id":"5675cbaf92514179e100365c","department":"Production","gender":1,"id":17451,"job":"Producer","name":"Cathy Schulman","profile_path":"/7WOIDFyZgZWtX152JW3kd5rxJPf.jpg"},{"credit_id":"5675cbbcc3a3681689003579","department":"Production","gender":2,"id":455,"job":"Producer","name":"Paul Haggis","profile_path":"/v2MadHJVrBAv0tEgs9H9PJ9y50z.jpg"},{"credit_id":"5675cbc8c3a36816800035d6","department":"Production","gender":2,"id":29787,"job":"Producer","name":"Mark R. Harris","profile_path":null},{"credit_id":"5675cbf092514179d4003796","department":"Production","gender":2,"id":137064,"job":"Producer","name":"Robert Moresco","profile_path":null},{"credit_id":"5675cc00c3a3681689003586","department":"Production","gender":2,"id":1896,"job":"Producer","name":"Don Cheadle","profile_path":"/b1EVJWdFn7a75qVYJgwO87W2TJU.jpg"},{"credit_id":"5675cc2ec3a368168e003b1f","department":"Production","gender":1,"id":20540,"job":"Co-Producer","name":"Randi Hiller","profile_path":null},{"credit_id":"5675cc38c3a3681685003735","department":"Production","gender":1,"id":7232,"job":"Co-Producer","name":"Sarah Finn","profile_path":null},{"credit_id":"5675cc45c3a3681683003667","department":"Production","gender":0,"id":59418,"job":"Co-Producer","name":"Betsy Danbury","profile_path":null},{"credit_id":"5675cd91c3a3681680003601","department":"Production","gender":2,"id":61051,"job":"Executive Producer","name":"Andrew Reimer","profile_path":null},{"credit_id":"5675cdd1c3a36816890035af","department":"Production","gender":2,"id":69306,"job":"Executive Producer","name":"Tom Nunan","profile_path":null},{"credit_id":"5675cdddc3a36816830036ad","department":"Production","gender":0,"id":17799,"job":"Executive Producer","name":"Marina Grasic","profile_path":null},{"credit_id":"5675cdf892514179d2003921","department":"Production","gender":0,"id":1526279,"job":"Associate Producer","name":"Dana Maksimovich","profile_path":null},{"credit_id":"5675ce2992514179e70036ca","department":"Costume & Make-Up","gender":1,"id":23973,"job":"Costume Design","name":"Linda M. Bass","profile_path":null},{"credit_id":"5675ce39925141691a0000b2","department":"Art","gender":0,"id":112307,"job":"Set Decoration","name":"Linda Lee Sutton","profile_path":null},{"credit_id":"5675ce49925141691a0000b4","department":"Art","gender":2,"id":25550,"job":"Production Design","name":"Laurence Bennett","profile_path":null},{"credit_id":"5675ce5592514179d2003929","department":"Art","gender":0,"id":1457819,"job":"Art Direction","name":"Brandee Dell'Aringa","profile_path":null},{"credit_id":"5675ceaac3a36816830036c5","department":"Sound","gender":0,"id":1551222,"job":"Sound mixer","name":"Richard Van Dyke","profile_path":null},{"credit_id":"5675cec292514179db00384d","department":"Sound","gender":0,"id":1355878,"job":"Supervising Sound Editor","name":"Sandy Gendler","profile_path":null},{"credit_id":"5675cee192514179d2003933","department":"Sound","gender":2,"id":1342242,"job":"Sound Re-Recording Mixer","name":"Rick Ash","profile_path":null},{"credit_id":"5675cef292514179db003856","department":"Sound","gender":2,"id":1387195,"job":"Sound Re-Recording Mixer","name":"Adam Jenkins","profile_path":null},{"credit_id":"5675cf12925141691a0000dd","department":"Sound","gender":2,"id":13177,"job":"Sound Re-Recording Mixer","name":"Marc Fishman","profile_path":null},{"credit_id":"5675cf2792514179d2003939","department":"Editing","gender":1,"id":1377293,"job":"Dialogue Editor","name":"Karen Vassar Triest","profile_path":null},{"credit_id":"5675cf4292514179e70036ef","department":"Editing","gender":0,"id":1404841,"job":"Dialogue Editor","name":"Zack Davis","profile_path":null},{"credit_id":"5675cf61925141691a0000e9","department":"Lighting","gender":0,"id":12598,"job":"Gaffer","name":"Dayton Nietert","profile_path":null},{"credit_id":"5675cf6ec3a3681680003635","department":"Lighting","gender":0,"id":1551224,"job":"Rigging Gaffer","name":"Victor Svimonoff","profile_path":null},{"credit_id":"5675cf91c3a36816830036e5","department":"Camera","gender":0,"id":1551226,"job":"First Assistant Camera","name":"Lee Blasingame","profile_path":null},{"credit_id":"5675cfa392514179e70036fc","department":"Camera","gender":2,"id":963861,"job":"Camera Operator","name":"Dana Gonzales","profile_path":null},{"credit_id":"5675cfc892514179e7003709","department":"Crew","gender":2,"id":182168,"job":"Stunt Coordinator","name":"Gary J. Wayton","profile_path":"/2xskyQVl79d9sfL9IIA7ebTJIp0.jpg"},{"credit_id":"5a1ddc98925141033306d2dc","department":"Production","gender":0,"id":17800,"job":"Executive Producer","name":"Jan Korbelin","profile_path":null},{"credit_id":"5a1ddd01c3a3680b9306f750","department":"Art","gender":0,"id":1802938,"job":"Construction Coordinator","name":"Jay Jergensen","profile_path":null},{"credit_id":"5a1ddd150e0a264cc406bfaf","department":"Art","gender":0,"id":1931768,"job":"Construction Foreman","name":"Bradford W. Shoemaker","profile_path":null},{"credit_id":"5a1ddd2cc3a3680b9a0742be","department":"Art","gender":0,"id":1931770,"job":"Leadman","name":"Daniel Brodo","profile_path":null},{"credit_id":"5a1ddd52925141033606f80e","department":"Art","gender":0,"id":1931772,"job":"Painter","name":"Steve Dennis","profile_path":null},{"credit_id":"5a1ddd649251410329070ee9","department":"Camera","gender":0,"id":1931773,"job":"Camera Intern","name":"Cole Gibson","profile_path":null},{"credit_id":"5a1ddd75925141033606f838","department":"Camera","gender":0,"id":1701736,"job":"Key Grip","name":"Art Bartels","profile_path":null},{"credit_id":"5a1ddd87925141032607218c","department":"Camera","gender":0,"id":1718524,"job":"Grip","name":"Jeff Goldberg","profile_path":null},{"credit_id":"5a1ddd9ac3a3680b9d06a00a","department":"Camera","gender":2,"id":91122,"job":"Aerial Director of Photography","name":"Dylan Goss","profile_path":"/lTqjDVe5mHGrBxWn7mOhO1kkL98.jpg"},{"credit_id":"5a1dddcec3a3680b9606eba3","department":"Camera","gender":0,"id":1931776,"job":"Steadicam Operator","name":"James M. Muro","profile_path":null},{"credit_id":"5a1ddddf925141033006bef7","department":"Costume & Make-Up","gender":1,"id":1146540,"job":"Hairstylist","name":"RaMona Fleetwood","profile_path":null},{"credit_id":"5a1dddeac3a3680b9606ebc1","department":"Costume & Make-Up","gender":0,"id":1418052,"job":"Key Hair Stylist","name":"Theraesa Rivers","profile_path":null},{"credit_id":"5a1dde01c3a3680b9306f83d","department":"Costume & Make-Up","gender":0,"id":1333900,"job":"Makeup Artist","name":"Michelle Vittone","profile_path":null},{"credit_id":"5a1dde17925141033906ec78","department":"Costume & Make-Up","gender":0,"id":1931778,"job":"Set Costumer","name":"Mary Cheung","profile_path":null},{"credit_id":"5a1dde22c3a3680b9d06a07b","department":"Costume & Make-Up","gender":0,"id":1064441,"job":"Set Dressing Artist","name":"James R. Barrows","profile_path":null},{"credit_id":"5a1dde390e0a264ccd070a83","department":"Crew","gender":0,"id":1931781,"job":"Chef","name":"Luis Brito","profile_path":null},{"credit_id":"5a1dde47c3a3680b9606ec17","department":"Crew","gender":0,"id":1931783,"job":"Driver","name":"Tony Barattini","profile_path":null},{"credit_id":"5a1dde690e0a264ccd070aa9","department":"Crew","gender":0,"id":1399694,"job":"Post Production Supervisor","name":"Brad Arensman","profile_path":null},{"credit_id":"5a1ddeaf0e0a264cbc0719f2","department":"Crew","gender":0,"id":1931788,"job":"Propmaker","name":"Oswaldo Rojas","profile_path":null},{"credit_id":"5a1ddebac3a3680b9306f8d8","department":"Art","gender":0,"id":1888928,"job":"Property Master","name":"Scott Ambrose","profile_path":null},{"credit_id":"5a1ddecf925141032406d6f9","department":"Crew","gender":0,"id":1931790,"job":"Scenic Artist","name":"Tek J. Smith","profile_path":null},{"credit_id":"5a1ddede925141033306d502","department":"Crew","gender":0,"id":1931791,"job":"Set Medic","name":"Barbara J. Keys","profile_path":null},{"credit_id":"5a1ddeffc3a3680b8a06da46","department":"Crew","gender":0,"id":1271793,"job":"Special Effects Coordinator","name":"Ron Trost","profile_path":null},{"credit_id":"5a1ddf100e0a264cca06e35e","department":"Crew","gender":0,"id":1931792,"job":"Stand In","name":"Paul Borbon","profile_path":null},{"credit_id":"5a1ddf20c3a3680b9306f941","department":"Crew","gender":0,"id":1931793,"job":"Stunts","name":"Richie Parker","profile_path":null},{"credit_id":"5a1ddf32c3a3680b9a074495","department":"Crew","gender":1,"id":1920135,"job":"Technical Supervisor","name":"Artaya Boonsoong","profile_path":null},{"credit_id":"5a1ddf68c3a3680b880703f6","department":"Crew","gender":0,"id":1931794,"job":"Transportation Co-Captain","name":"Juan Ramirez","profile_path":null},{"credit_id":"5a1ddf77925141032406d7a5","department":"Crew","gender":0,"id":1430999,"job":"Transportation Coordinator","name":"Michael Perrotti","profile_path":null},{"credit_id":"5a1ddf91c3a3680b8f06ebb8","department":"Production","gender":0,"id":59418,"job":"Unit Production Manager","name":"Betsy Danbury","profile_path":null},{"credit_id":"5a1ddfa50e0a264cc80728f2","department":"Crew","gender":0,"id":1402952,"job":"Unit Publicist","name":"Erik Bright","profile_path":null},{"credit_id":"5a1ddfb8c3a3680b9306f9c1","department":"Crew","gender":0,"id":112289,"job":"Video Assist Operator","name":"Chris Shadley","profile_path":null},{"credit_id":"5a1ddfef0e0a264cc406c1fc","department":"Directing","gender":0,"id":1602874,"job":"First Assistant Director","name":"Scott Cameron","profile_path":null},{"credit_id":"5a1de0cf0e0a264cc8072a02","department":"Lighting","gender":0,"id":1301634,"job":"Electrician","name":"Paul Arnold","profile_path":null},{"credit_id":"5a1de0f3c3a3680b9606ee59","department":"Production","gender":1,"id":1776547,"job":"Casting Associate","name":"Erika Sellin","profile_path":null},{"credit_id":"5a1de10ac3a3680b8f06ed2c","department":"Production","gender":0,"id":1257919,"job":"Executive In Charge Of Production","name":"Robert Katz","profile_path":null},{"credit_id":"5a1de123c3a3680b9306fb07","department":"Production","gender":0,"id":1338456,"job":"Location Manager","name":"Jennifer Dunne","profile_path":null},{"credit_id":"5a1de132925141033906ef1d","department":"Production","gender":0,"id":1635077,"job":"Production Accountant","name":"Tanoa Parks","profile_path":null},{"credit_id":"5a1de143925141033906ef31","department":"Production","gender":0,"id":1931796,"job":"Production Coordinator","name":"Andrew Blau","profile_path":null},{"credit_id":"5a1de154c3a3680b8a06dc1d","department":"Production","gender":1,"id":1538374,"job":"Production Supervisor","name":"Mads Hansen","profile_path":null},{"credit_id":"5a1de1679251410329071280","department":"Sound","gender":0,"id":1342654,"job":"Boom Operator","name":"Carl Fischer","profile_path":null},{"credit_id":"5a1de1c5925141032c07037e","department":"Sound","gender":0,"id":1636393,"job":"Music Supervisor","name":"Richard Glasser","profile_path":null},{"credit_id":"5a1de205c3a3680b8807065d","department":"Visual Effects","gender":0,"id":1931798,"job":"Digital Compositors","name":"Andy Chih-Jen Chang","profile_path":null},{"credit_id":"5a1de218925141033306d7ab","department":"Visual Effects","gender":2,"id":1409234,"job":"Visual Effects Coordinator","name":"Glenn Morris","profile_path":null},{"credit_id":"5a1de229925141032c0703d9","department":"Visual Effects","gender":0,"id":1400343,"job":"Visual Effects Producer","name":"Ian Noe","profile_path":null},{"credit_id":"5a1de23ec3a3680b9d06a3cb","department":"Visual Effects","gender":1,"id":1409236,"job":"Visual Effects Supervisor","name":"Payam Shohadai","profile_path":null},{"credit_id":"5a1de24fc3a3680b9d06a3da","department":"Writing","gender":0,"id":1695275,"job":"Storyboard","name":"Jonathan Woods","profile_path":null},{"credit_id":"5a1de263925141032406da52","department":"Crew","gender":0,"id":1739564,"job":"Studio Teachers","name":"Jack Stern","profile_path":null},{"credit_id":"5a1de2759251410329071386","department":"Crew","gender":1,"id":13221,"job":"Title Graphics","name":"J. Kathryn Landholt","profile_path":null},{"credit_id":"5a1de28a925141033906f06f","department":"Production","gender":0,"id":1931799,"job":"Finance","name":"Richard D. Lewis","profile_path":null},{"credit_id":"5a1de299925141033606fd08","department":"Sound","gender":0,"id":13224,"job":"Dolby Consultant","name":"Andy Potvin","profile_path":null},{"credit_id":"5bb668bf0e0a26339301574b","department":"Sound","gender":2,"id":2141653,"job":"Music Editor","name":"James Burt","profile_path":null},{"credit_id":"5cdc96ba0e0a264c87cce9e9","department":"Directing","gender":0,"id":1841641,"job":"Second Assistant Director","name":"Simone Farber","profile_path":null},{"credit_id":"5cdc96cbc3a36872e3c3a0e0","department":"Directing","gender":2,"id":18299,"job":"Second Second Assistant Director","name":"Ime Etuk","profile_path":null},{"credit_id":"5cdc96db9251416e32cf564f","department":"Directing","gender":0,"id":2244241,"job":"Third Assistant Director","name":"Christian Pichler","profile_path":null},{"credit_id":"5cdc96f3c3a3680fd4c5c974","department":"Art","gender":0,"id":1815190,"job":"Creative Director","name":"Michael McIntyre","profile_path":null},{"credit_id":"5cdc96ff0e0a26045cd17418","department":"Sound","gender":0,"id":1404901,"job":"ADR Mixer","name":"Greg Steele","profile_path":null},{"credit_id":"5cdc97140e0a265585d1a920","department":"Sound","gender":0,"id":2045922,"job":"ADR Recordist","name":"Julie Altus","profile_path":null},{"credit_id":"5cdc97270e0a26045cd17422","department":"Sound","gender":0,"id":91094,"job":"Foley Artist","name":"Joan Rowe","profile_path":null},{"credit_id":"5cdc973d0e0a265585d1a957","department":"Sound","gender":0,"id":1760573,"job":"Foley Mixer","name":"Darrin Mann","profile_path":null},{"credit_id":"5cdc974f9251416b5bd18672","department":"Sound","gender":0,"id":1715684,"job":"Utility Sound","name":"Rocky Quiroz","profile_path":null},{"credit_id":"5cdc976c0e0a265585d1a986","department":"Crew","gender":0,"id":2313763,"job":"Special Effects Technician","name":"Dan Edwards","profile_path":null},{"credit_id":"5cdc977a0e0a262dcfccb182","department":"Camera","gender":0,"id":2313764,"job":"Additional Second Assistant Camera","name":"James 'Spud' Danicic","profile_path":null},{"credit_id":"5cdc97899251412a38cf7c91","department":"Camera","gender":0,"id":1913993,"job":"Assistant Camera","name":"Matthew A. Del Ruth","profile_path":null},{"credit_id":"5cdc9797925141767ecf58a3","department":"Camera","gender":0,"id":1931795,"job":"Best Boy Grip","name":"Bruce Chimerofsky","profile_path":null},{"credit_id":"5cdc97a4c3a3684125c21cd9","department":"Camera","gender":0,"id":1687137,"job":"Camera Loader","name":"Raul Riveros","profile_path":null},{"credit_id":"5cdc97c30e0a26045cd174cd","department":"Camera","gender":0,"id":2313766,"job":"Digital Imaging Technician","name":"David Fred Masselink","profile_path":null},{"credit_id":"5cdc97ce9251416e32cf5706","department":"Camera","gender":0,"id":1733129,"job":"Dolly Grip","name":"James D. Wickman","profile_path":null},{"credit_id":"5cdc97f79251417660cf4d18","department":"Camera","gender":0,"id":2301920,"job":"Second Assistant Camera","name":"Kirk Bloom","profile_path":null},{"credit_id":"5cdc9807c3a36831a3c24b9c","department":"Production","gender":1,"id":1681846,"job":"Casting Assistant","name":"Amy Greene","profile_path":null},{"credit_id":"5cdc9817c3a3683d17c21700","department":"Costume & Make-Up","gender":0,"id":2313768,"job":"Wardrobe Intern","name":"Leyla Jabbar","profile_path":null},{"credit_id":"5cdc98230e0a26407dd37946","department":"Costume & Make-Up","gender":0,"id":2313769,"job":"Wardrobe Supervisor","name":"Gail Just","profile_path":null},{"credit_id":"5cdc982fc3a36836f6c6e2a7","department":"Editing","gender":0,"id":2313770,"job":"Assistant Editor","name":"J.D. McDonald","profile_path":null},{"credit_id":"5cdc983a0e0a26045cd17602","department":"Editing","gender":0,"id":1822665,"job":"Colorist","name":"Ed Twiford","profile_path":null},{"credit_id":"5cdc984b0e0a26407dd3796b","department":"Editing","gender":2,"id":13181,"job":"Digital Colorist","name":"Adam Hawkey","profile_path":null},{"credit_id":"5cdc9860c3a36831a3c24c5e","department":"Production","gender":0,"id":2313772,"job":"Post Production Coordinator","name":"Joel T. Pashby","profile_path":null},{"credit_id":"5cdc986ec3a3683d17c21758","department":"Production","gender":0,"id":2034678,"job":"Assistant Location Manager","name":"David Diamond","profile_path":null},{"credit_id":"5cdc98810e0a26407dd37a4d","department":"Sound","gender":2,"id":4140,"job":"Music Arranger","name":"Mark Isham","profile_path":"/juP82LbS9chU3VXgelb7CICBN2Q.jpg"},{"credit_id":"5cdc98930e0a264c87ccebe0","department":"Sound","gender":1,"id":1558994,"job":"Music Coordinator","name":"Rebecca Rienks","profile_path":null},{"credit_id":"5cdc98a80e0a262d10ccba51","department":"Crew","gender":0,"id":1931781,"job":"Catering","name":"Luis Brito","profile_path":null},{"credit_id":"5cdc98c492514121dad643ce","department":"Production","gender":0,"id":1677318,"job":"Extras Casting","name":"Jimmy Jue","profile_path":null},{"credit_id":"5cdc98dfc3a36831dec975a6","department":"Production","gender":0,"id":2313776,"job":"First Assistant Accountant","name":"Tiffany Thomas","profile_path":null},{"credit_id":"5cdc98edc3a3684a97c9bf36","department":"Production","gender":0,"id":1361755,"job":"Key Set Production Assistant","name":"Jordan Brendan Finnegan","profile_path":null},{"credit_id":"5cdc98fe0e0a264c87ccec80","department":"Production","gender":0,"id":2047518,"job":"Payroll Accountant","name":"Paul Giorgi","profile_path":null},{"credit_id":"5cdc990c0e0a26045cd176cc","department":"Crew","gender":2,"id":1632066,"job":"Pilot","name":"Peter McKernan","profile_path":"/y9TwHiOhGphwiedYtgW97AxCUtk.jpg"},{"credit_id":"5cdc99189251413606d3099a","department":"Production","gender":2,"id":2710,"job":"Production Assistant","name":"James Cameron","profile_path":"/4TjSh3Er5LIOvFcB5inaRDPrBKu.jpg"},{"credit_id":"5cdc99629251410c9dd3d425","department":"Production","gender":0,"id":1646249,"job":"Production Executive","name":"Evan Edelist","profile_path":null},{"credit_id":"5cdc9976c3a36836f6c6e5cd","department":"Production","gender":0,"id":2313778,"job":"Production Secretary","name":"Dale Ottley","profile_path":null}]}