{"id":2690,"cast":[{"cast_id":13,"character":"Nestor Patou","credit_id":"52fe4365c3a36847f8051203","gender":2,"id":3151,"name":"Jack Lemmon","order":0,"profile_path":"/chZmNRYMtqkiDlatprGDH4BzGqG.jpg"},{"cast_id":14,"character":"Irma La Douce","credit_id":"52fe4365c3a36847f8051207","gender":1,"id":4090,"name":"Shirley MacLaine","order":1,"profile_path":"/faG5S4EOVaGHNf1CwZryGcHCE4e.jpg"},{"cast_id":15,"character":"Moustache","credit_id":"52fe4365c3a36847f805120b","gender":2,"id":23708,"name":"Lou Jacobi","order":2,"profile_path":"/3mZd7AemcMf57gKeINMj0wPs6V5.jpg"},{"cast_id":16,"character":"Police sergeant","credit_id":"52fe4365c3a36847f805120f","gender":2,"id":14834,"name":"Cliff Osmond","order":3,"profile_path":"/tTxv0TKz8SDgKAhayx6LJsQOXU4.jpg"},{"cast_id":17,"character":"Hippolyte","credit_id":"52fe4365c3a36847f8051213","gender":2,"id":27034,"name":"Bruce Yarnell","order":4,"profile_path":"/Aa6vOxmG7bQXvM6fEYU9x8BuyBt.jpg"},{"cast_id":18,"character":"Lolita","credit_id":"52fe4365c3a36847f8051217","gender":1,"id":4097,"name":"Hope Holiday","order":5,"profile_path":"/j4jpTC8PapBbWEn13b3N9yqPCxl.jpg"},{"cast_id":19,"character":"Insp. Lefevre","credit_id":"52fe4365c3a36847f805121b","gender":2,"id":18860,"name":"Herschel Bernardi","order":6,"profile_path":"/k386JDVsnHVTEc00Q7QZhHcJNPe.jpg"},{"cast_id":20,"character":"Amazon Annie","credit_id":"52fe4365c3a36847f805121f","gender":1,"id":3161,"name":"Joan Shawlee","order":7,"profile_path":"/bmMsmZ2hcVYFYHs1HhtfuqopGAX.jpg"},{"cast_id":21,"character":"Andre","credit_id":"52fe4365c3a36847f8051223","gender":2,"id":27035,"name":"Paul Dubov","order":8,"profile_path":"/vPslqnIMKpqRHHlIJTleLaia0Pr.jpg"},{"cast_id":22,"character":"Concierge","credit_id":"52fe4365c3a36847f8051227","gender":2,"id":19786,"name":"Howard McNear","order":9,"profile_path":"/pqe7uwiUrPXruIuYefjO5MOtEFI.jpg"},{"cast_id":26,"character":"Suzette Wong","credit_id":"5aa5f6920e0a263dcd001f21","gender":1,"id":4592,"name":"Tura Satana","order":10,"profile_path":"/f6zYcgErVgJ9a3UgkVlLPW37wy.jpg"},{"cast_id":27,"character":"Tattooed Sailor","credit_id":"5d0586580e0a267fa9cbcd35","gender":2,"id":19138,"name":"Bill Bixby","order":11,"profile_path":"/jkFwca4IIvzRN88ay4chyvFj4lk.jpg"}],"crew":[{"credit_id":"52fe4365c3a36847f80511bd","department":"Directing","gender":2,"id":3146,"job":"Director","name":"Billy Wilder","profile_path":"/nWV9BDDCbRegP7etiPjl3vYnJEq.jpg"},{"credit_id":"52fe4365c3a36847f80511c3","department":"Writing","gender":2,"id":3146,"job":"Screenplay","name":"Billy Wilder","profile_path":"/nWV9BDDCbRegP7etiPjl3vYnJEq.jpg"},{"credit_id":"52fe4365c3a36847f80511c9","department":"Writing","gender":2,"id":3147,"job":"Screenplay","name":"I. A. L. Diamond","profile_path":"/tm4mgbRqYYQMqbIps8F6iKmOBM9.jpg"},{"credit_id":"52fe4365c3a36847f80511cf","department":"Production","gender":2,"id":3147,"job":"Producer","name":"I. A. L. Diamond","profile_path":"/tm4mgbRqYYQMqbIps8F6iKmOBM9.jpg"},{"credit_id":"52fe4365c3a36847f80511d5","department":"Production","gender":2,"id":3146,"job":"Producer","name":"Billy Wilder","profile_path":"/nWV9BDDCbRegP7etiPjl3vYnJEq.jpg"},{"credit_id":"52fe4365c3a36847f80511db","department":"Production","gender":0,"id":27033,"job":"Producer","name":"Edward L. Alperson","profile_path":null},{"credit_id":"52fe4365c3a36847f80511e1","department":"Production","gender":2,"id":3159,"job":"Producer","name":"Doane Harrison","profile_path":null},{"credit_id":"52fe4365c3a36847f80511e7","department":"Production","gender":2,"id":4103,"job":"Producer","name":"Alexandre Trauner","profile_path":null},{"credit_id":"52fe4365c3a36847f80511ed","department":"Sound","gender":2,"id":5805,"job":"Original Music Composer","name":"André Previn","profile_path":null},{"credit_id":"52fe4365c3a36847f80511f3","department":"Camera","gender":2,"id":4101,"job":"Director of Photography","name":"Joseph LaShelle","profile_path":"/3j8m5eDzhinBJeUscfNZWhJn9ch.jpg"},{"credit_id":"52fe4365c3a36847f80511f9","department":"Editing","gender":2,"id":4102,"job":"Editor","name":"Daniel Mandell","profile_path":null},{"credit_id":"52fe4365c3a36847f80511ff","department":"Costume & Make-Up","gender":2,"id":4127,"job":"Costume Design","name":"Orry-Kelly","profile_path":"/zDyC5sYHLtS5Kb3A1QDyoVKXLiL.jpg"},{"credit_id":"52fe4365c3a36847f805122d","department":"Writing","gender":0,"id":1123345,"job":"Author","name":"Alexandre Breffort","profile_path":null},{"credit_id":"52fe4365c3a36847f8051233","department":"Production","gender":2,"id":1263,"job":"Casting","name":"Lynn Stalmaster","profile_path":"/rhyzo2qgsGAXIpGTN5OabbZU95U.jpg"},{"credit_id":"52fe4365c3a36847f8051239","department":"Art","gender":2,"id":4103,"job":"Art Direction","name":"Alexandre Trauner","profile_path":null}]}