{"id":2701,"cast":[{"cast_id":1,"character":"Abraham","credit_id":"52fe4366c3a36847f8051821","gender":2,"id":194,"name":"Richard Harris","order":0,"profile_path":"/51wDHVFNqrYgvUBMOcACAt4sJU9.jpg"},{"cast_id":2,"character":"Sara","credit_id":"52fe4366c3a36847f8051825","gender":1,"id":10767,"name":"Barbara Hershey","order":1,"profile_path":"/kCKQX9OBCQ7VPsxzmEXHFsN3OwC.jpg"},{"cast_id":3,"character":"Terach","credit_id":"52fe4366c3a36847f8051829","gender":2,"id":12259,"name":"Vittorio Gassman","order":2,"profile_path":"/qjSYEX5zQuuJzRvznpFz5Xqfbvv.jpg"},{"cast_id":4,"character":"Hagar","credit_id":"52fe4366c3a36847f805182d","gender":0,"id":27188,"name":"Carolina Rosi","order":3,"profile_path":null},{"cast_id":5,"character":"Lot","credit_id":"52fe4366c3a36847f8051831","gender":2,"id":20440,"name":"Andrea Prodan","order":4,"profile_path":"/zUoyASv2z6hZOudGXgcrDgKHiYR.jpg"},{"cast_id":6,"character":"Eliezer","credit_id":"52fe4366c3a36847f8051835","gender":2,"id":3757,"name":"Gottfried John","order":5,"profile_path":"/li8nXn68uv62jxZcI1FGQeuvGmi.jpg"},{"cast_id":7,"character":"Nahor","credit_id":"52fe4366c3a36847f8051839","gender":2,"id":2449,"name":"Kevin McNally","order":6,"profile_path":"/fIJF3TZn8ckHkcl44oX77GvPv9e.jpg"},{"cast_id":8,"character":"Lots Frau","credit_id":"52fe4366c3a36847f805183d","gender":0,"id":27189,"name":"Simona Ferraro","order":7,"profile_path":null},{"cast_id":9,"character":"Serug","credit_id":"52fe4366c3a36847f8051841","gender":0,"id":27190,"name":"Tom Radcliffe","order":8,"profile_path":null},{"cast_id":10,"character":"Micha","credit_id":"52fe4366c3a36847f8051845","gender":0,"id":27191,"name":"Jude Alderson","order":9,"profile_path":null},{"cast_id":11,"character":"Reuma","credit_id":"52fe4366c3a36847f8051849","gender":0,"id":27192,"name":"Evelina Meghnagi","order":10,"profile_path":"/zr6aeh8En73Qs9D7xM2eChLLWHK.jpg"},{"cast_id":12,"character":"Ismael als Kind","credit_id":"52fe4366c3a36847f805184d","gender":0,"id":27193,"name":"Danny Mertsoy","order":11,"profile_path":null},{"cast_id":13,"character":"Ismael als Heranwachsender","credit_id":"52fe4366c3a36847f8051851","gender":0,"id":27194,"name":"Giuseppe Peluso","order":12,"profile_path":null},{"cast_id":14,"character":"Isaak als Kind","credit_id":"52fe4366c3a36847f8051855","gender":2,"id":24617,"name":"Timur Yusef","order":13,"profile_path":null},{"cast_id":15,"character":"Isaak als Heranwachsender","credit_id":"52fe4366c3a36847f8051859","gender":0,"id":27195,"name":"Taylor Scipio","order":14,"profile_path":null},{"cast_id":16,"character":"Melchisedek","credit_id":"52fe4366c3a36847f805185d","gender":0,"id":4819,"name":"Paolo Bonacelli","order":15,"profile_path":"/7h2EJQ19m9pZCfyGEoXb8aEFIF2.jpg"},{"cast_id":17,"character":"Mamre","credit_id":"52fe4366c3a36847f8051861","gender":2,"id":8772,"name":"Mattia Sbragia","order":16,"profile_path":"/vCxzBHo6Ge7QhocOq4o8GlIIjsd.jpg"},{"cast_id":18,"character":"Eschkol","credit_id":"52fe4366c3a36847f8051865","gender":2,"id":23962,"name":"Christian Kohlund","order":17,"profile_path":"/6kiGbf4ml11wii9QnpwMHPHZsyg.jpg"},{"cast_id":19,"character":"König Arjoch","credit_id":"52fe4366c3a36847f8051869","gender":2,"id":26669,"name":"Vincent Riotta","order":18,"profile_path":"/emNPSoWXnj6K5o8jrJP0E8dTWa0.jpg"},{"cast_id":20,"character":"König von Sodom","credit_id":"52fe4366c3a36847f805186d","gender":2,"id":14149,"name":"Renato Scarpa","order":19,"profile_path":"/4jANi4vGdTqFG7a5OjtbM9ikwOe.jpg"},{"cast_id":21,"character":"König von Haran","credit_id":"52fe4366c3a36847f8051871","gender":2,"id":27196,"name":"Mario Erpichini","order":20,"profile_path":"/yO3NdlUhq989Bpq6Gnq9aIuodQd.jpg"},{"cast_id":22,"character":"König Tidal","credit_id":"52fe4366c3a36847f8051875","gender":0,"id":27197,"name":"Emidio La Vella","order":21,"profile_path":null},{"cast_id":23,"character":"Gocemar","credit_id":"52fe4366c3a36847f8051879","gender":2,"id":27198,"name":"Orso Maria Guerrini","order":22,"profile_path":"/9Gpe7JoCuCeKqiriAqDsrvOVBLi.jpg"},{"cast_id":24,"character":"Ägyptischer Priester","credit_id":"52fe4366c3a36847f805187d","gender":2,"id":27199,"name":"Francesco Carnelutti","order":23,"profile_path":null},{"cast_id":25,"character":"Ägyptischer Hauptmann","credit_id":"52fe4366c3a36847f8051881","gender":0,"id":7551,"name":"Mauro Marino","order":24,"profile_path":"/lvjZgHvIqhPLTWcEFgj5EMjh3iM.jpg"},{"cast_id":26,"character":"Ägyptischer Hauptmann","credit_id":"52fe4366c3a36847f8051885","gender":0,"id":27200,"name":"Maurizio Benazzo","order":25,"profile_path":null},{"cast_id":27,"character":"Sodomiter","credit_id":"52fe4366c3a36847f8051889","gender":0,"id":27201,"name":"Paco Reconti","order":26,"profile_path":"/mFmBpMr1FHAV2AJphHQKNnYoCYZ.jpg"},{"cast_id":28,"character":"Serug als Kind","credit_id":"52fe4366c3a36847f805188d","gender":0,"id":27202,"name":"Aziz Khaldoun","order":27,"profile_path":null},{"cast_id":29,"character":"Sklavenhändler","credit_id":"52fe4366c3a36847f8051891","gender":2,"id":24603,"name":"Rodolfo Corsato","order":28,"profile_path":"/wQJh6i6WWv3xIAjQb0CRv6V2OxZ.jpg"},{"cast_id":30,"character":"Engel","credit_id":"52fe4366c3a36847f8051895","gender":0,"id":27203,"name":"Francesco Siciliano","order":29,"profile_path":"/nrS0HGtH0j5LRuiQAGH7E9dDqrz.jpg"},{"cast_id":31,"character":"Regu","credit_id":"52fe4366c3a36847f8051899","gender":2,"id":2980,"name":"Nadim Sawalha","order":30,"profile_path":"/94kMNtU2FYXruX4BOOjWrWkoe2x.jpg"},{"cast_id":32,"character":"König Kedor-Laomer","credit_id":"52fe4366c3a36847f805189d","gender":0,"id":24586,"name":"Joel Proust","order":31,"profile_path":null},{"cast_id":49,"character":"Königsberater","credit_id":"52fe4366c3a36847f8051901","gender":2,"id":24498,"name":"John McEnery","order":32,"profile_path":"/nDbOOKZP7F0zuhGVIitzOlh162C.jpg"},{"cast_id":50,"character":"Pharao","credit_id":"52fe4366c3a36847f8051905","gender":2,"id":12150,"name":"Maximilian Schell","order":33,"profile_path":"/1KqKnArTDYz6L6M8h9nN4RLP8YE.jpg"}],"crew":[{"credit_id":"52fe4366c3a36847f80518a3","department":"Directing","gender":2,"id":15663,"job":"Director","name":"Joseph Sargent","profile_path":"/caO0AI5r8xT2C3yCo8czB8DA1nr.jpg"},{"credit_id":"52fe4366c3a36847f80518a9","department":"Writing","gender":0,"id":27204,"job":"Screenplay","name":"Robert McKee","profile_path":null},{"credit_id":"52fe4366c3a36847f80518af","department":"Production","gender":2,"id":24580,"job":"Producer","name":"Lorenzo Minoli","profile_path":null},{"credit_id":"52fe4366c3a36847f80518b5","department":"Production","gender":2,"id":24582,"job":"Executive Producer","name":"Gerald Rafshoon","profile_path":null},{"credit_id":"52fe4366c3a36847f80518bb","department":"Sound","gender":2,"id":24583,"job":"Original Music Composer","name":"Marco Frisina","profile_path":null},{"credit_id":"52fe4366c3a36847f80518c1","department":"Sound","gender":2,"id":1259,"job":"Original Music Composer","name":"Ennio Morricone","profile_path":"/tlntfyflyEHgJTFjqIgg8P8UIx9.jpg"},{"credit_id":"52fe4366c3a36847f80518c7","department":"Camera","gender":2,"id":23951,"job":"Director of Photography","name":"Raffaele Mertes","profile_path":null},{"credit_id":"52fe4366c3a36847f80518cd","department":"Editing","gender":2,"id":16207,"job":"Editor","name":"Michael Brown","profile_path":"/cl9PSNSf1rynsAmchVzkeD5iAhC.jpg"},{"credit_id":"52fe4366c3a36847f80518d3","department":"Production","gender":2,"id":8313,"job":"Casting","name":"Jeremy Zimmermann","profile_path":null},{"credit_id":"52fe4366c3a36847f80518d9","department":"Production","gender":1,"id":8753,"job":"Casting","name":"Shaila Rubin","profile_path":null},{"credit_id":"52fe4366c3a36847f80518df","department":"Art","gender":0,"id":23956,"job":"Production Design","name":"Paolo Biagetti","profile_path":null},{"credit_id":"52fe4366c3a36847f80518e5","department":"Art","gender":0,"id":14590,"job":"Production Design","name":"Enrico Sabbatini","profile_path":null},{"credit_id":"52fe4366c3a36847f80518eb","department":"Costume & Make-Up","gender":0,"id":14590,"job":"Costume Design","name":"Enrico Sabbatini","profile_path":null},{"credit_id":"52fe4366c3a36847f80518f1","department":"Costume & Make-Up","gender":0,"id":27205,"job":"Makeup Artist","name":"Luigi Rocchetti","profile_path":null},{"credit_id":"52fe4366c3a36847f80518f7","department":"Costume & Make-Up","gender":0,"id":23365,"job":"Makeup Artist","name":"Mario Michisanti","profile_path":null},{"credit_id":"52fe4366c3a36847f80518fd","department":"Costume & Make-Up","gender":0,"id":27206,"job":"Hairstylist","name":"Gianna Viola","profile_path":null}]}