{"id":3565,"cast":[{"cast_id":6,"character":"Bill","credit_id":"52fe439dc3a36847f8061cfb","gender":2,"id":32923,"name":"Brian Aherne","order":0,"profile_path":"/jX8H9PYZTuzFqxEa76W0dEVzKWF.jpg"},{"cast_id":7,"character":"Nell","credit_id":"52fe439dc3a36847f8061cff","gender":1,"id":32924,"name":"Elissa Landi","order":1,"profile_path":"/4EH1Hwm61Iu5LnskyjkbdtYx0zm.jpg"},{"cast_id":8,"character":"Bert","credit_id":"52fe439dc3a36847f8061d03","gender":0,"id":32925,"name":"Cyril McLaglen","order":2,"profile_path":null},{"cast_id":9,"character":"Kate","credit_id":"52fe439dc3a36847f8061d07","gender":0,"id":32926,"name":"Norah Baring","order":3,"profile_path":"/b8V6QpFpOz6bqQ7LBC7f4q4TXNe.jpg"}],"crew":[{"credit_id":"52fe439cc3a36847f8061cdf","department":"Directing","gender":2,"id":32919,"job":"Director","name":"Anthony Asquith","profile_path":"/7HcBZ21Huhgwa4bEsxm8KPv5dZj.jpg"},{"credit_id":"52fe439cc3a36847f8061ce5","department":"Writing","gender":2,"id":32919,"job":"Screenplay","name":"Anthony Asquith","profile_path":"/7HcBZ21Huhgwa4bEsxm8KPv5dZj.jpg"},{"credit_id":"52fe439cc3a36847f8061ceb","department":"Camera","gender":0,"id":32920,"job":"Director of Photography","name":"Stanley Rodwell","profile_path":null},{"credit_id":"52fe439cc3a36847f8061cf1","department":"Art","gender":2,"id":32921,"job":"Art Direction","name":"Ian Campbell-Gray","profile_path":null},{"credit_id":"52fe439dc3a36847f8061cf7","department":"Lighting","gender":2,"id":32922,"job":"Lighting Technician","name":"Karl Fischer","profile_path":null}]}