{"adult":false,"backdrop_path":"/jIcZ4pNno85AETjfotBXmug3BtJ.jpg","belongs_to_collection":null,"budget":0,"genres":[{"id":27,"name":"Horror"},{"id":10770,"name":"TV Movie"}],"homepage":null,"id":4337,"imdb_id":"tt0109275","original_language":"en","original_title":"The Birds II: Land's End","overview":"Birds go berserk and turn against mankind.","popularity":2.299,"poster_path":"/lKPb3qGIjySTxQJvv4Jz2NkAmQL.jpg","production_companies":[{"id":63813,"logo_path":null,"name":"Rosemont Productions International","origin_country":"US"},{"id":4683,"logo_path":null,"name":"MCA Television Entertainment (MTE)","origin_country":""}],"production_countries":[{"iso_3166_1":"US","name":"United States of America"}],"release_date":"1994-03-19","revenue":0,"runtime":87,"spoken_languages":[{"iso_639_1":"en","name":"English"}],"status":"Released","tagline":"History Has A Nasty Way Of Repeating Itself.","title":"The Birds II: Land's End","video":false,"vote_average":2.5,"vote_count":15}