{"id":4639,"cast":[{"cast_id":10,"character":"Cleve","credit_id":"52fe43d0c3a36847f8071ca3","gender":2,"id":4512,"name":"James Woods","order":0,"profile_path":"/fl5Jx1WFvBcg1b9VZRfXTH6LPUE.jpg"},{"cast_id":11,"character":"Dennis Meechum","credit_id":"52fe43d0c3a36847f8071ca7","gender":2,"id":6197,"name":"Brian Dennehy","order":1,"profile_path":"/3xauJUPivBQAqAbfnbwcj6vHKYz.jpg"},{"cast_id":12,"character":"Roberta Gillian","credit_id":"52fe43d0c3a36847f8071cab","gender":1,"id":21618,"name":"Victoria Tennant","order":2,"profile_path":"/8l6jWaq4o2us3KtMD9hhocaMajR.jpg"},{"cast_id":13,"character":"Holly Meechum","credit_id":"52fe43d0c3a36847f8071caf","gender":1,"id":38690,"name":"Allison Balson","order":3,"profile_path":"/VjZ6PsFemlHuXvELb8xyuw4R4R.jpg"},{"cast_id":14,"character":"David Madlock","credit_id":"52fe43d0c3a36847f8071cb3","gender":2,"id":1165,"name":"Paul Shenar","order":4,"profile_path":"/pKKAqHEVKXLFVik1zWT59vaXRbk.jpg"},{"cast_id":15,"character":"Graham","credit_id":"52fe43d0c3a36847f8071cb7","gender":2,"id":14102,"name":"George Coe","order":5,"profile_path":"/2ygklxHSWcNuWg4hjZe5J9MlzNR.jpg"},{"cast_id":16,"character":"Mrs. Foster","credit_id":"52fe43d0c3a36847f8071cbb","gender":1,"id":38691,"name":"Anne Pitoniak","order":6,"profile_path":"/zcQf85EI3UyqDc9SKqrVCSKIOx5.jpg"},{"cast_id":17,"character":"Cleve's mother","credit_id":"557b25cb9251414f24000015","gender":1,"id":152696,"name":"Mary Carver","order":7,"profile_path":null},{"cast_id":19,"character":"Annie","credit_id":"557b25e69251414f1a00001a","gender":1,"id":99885,"name":"Kathleen Lloyd","order":9,"profile_path":"/7cBzFpCioOZt92HKOTJmwxlRdDt.jpg"},{"cast_id":20,"character":"Monks","credit_id":"557b25eac3a3683e91000017","gender":2,"id":14545,"name":"Sully Boyar","order":10,"profile_path":"/joJktsmK4VLCw5ZnUMR64V9hZyG.jpg"},{"cast_id":21,"character":"Harold, Cleve's father","credit_id":"557b25fec3a3683e98000012","gender":2,"id":4974,"name":"Charles Tyner","order":11,"profile_path":"/6OHlhUQcMXIMIkqIskBw4tK2Mp7.jpg"},{"cast_id":22,"character":"Taxi Driver","credit_id":"557b263b9251414f16000011","gender":0,"id":112963,"name":"E. Brian Dean","order":12,"profile_path":null},{"cast_id":25,"character":"Pearlman","credit_id":"557b265bc3a3683e91000023","gender":2,"id":1476546,"name":"Jeffrey Josephson","order":15,"profile_path":"/BkBGgfdB3jTIAONiyQeNSNZOTA.jpg"},{"cast_id":26,"character":"Thorn","credit_id":"557b2667c3a3683e9800001c","gender":0,"id":52146,"name":"Edward Blackoff","order":16,"profile_path":null},{"cast_id":45,"character":"Carter","credit_id":"59da7242c3a3686227043d3b","gender":2,"id":5950,"name":"Seymour Cassel","order":17,"profile_path":"/atWyQvsLNjmXP5dxsOiaf5Qg9j.jpg"},{"cast_id":46,"character":"Longshoreman #1","credit_id":"5c4140299251417ba0ad604b","gender":2,"id":106730,"name":"Branscombe Richmond","order":18,"profile_path":"/d8i0tFr9JDfhGUhKtr25HnZey3s.jpg"}],"crew":[{"credit_id":"52fe43d0c3a36847f8071c6f","department":"Directing","gender":2,"id":38689,"job":"Director","name":"John Flynn","profile_path":"/xljUB8XNCvYRX6XPkMXwt4Ah38w.jpg"},{"credit_id":"52fe43d0c3a36847f8071c81","department":"Sound","gender":0,"id":24954,"job":"Original Music Composer","name":"Jay Ferguson","profile_path":"/39MWXPmJT8dp2qALFlCAFLBzQkd.jpg"},{"credit_id":"52fe43d0c3a36847f8071c87","department":"Camera","gender":2,"id":17765,"job":"Director of Photography","name":"Fred Murphy","profile_path":"/oLzSw5wj6X3H5FYIQuXruf8TkaW.jpg"},{"credit_id":"52fe43d0c3a36847f8071c8d","department":"Editing","gender":2,"id":17816,"job":"Editor","name":"David Rosenbloom","profile_path":"/zvScb6TbJ1EDwKVY1kpyiGVknzU.jpg"},{"credit_id":"52fe43d0c3a36847f8071c93","department":"Production","gender":0,"id":21558,"job":"Casting","name":"Diane Dimeo","profile_path":null},{"credit_id":"52fe43d0c3a36847f8071c99","department":"Production","gender":2,"id":9585,"job":"Casting","name":"Michael McLean","profile_path":null},{"credit_id":"557b26c1c3a3683e9100002e","department":"Writing","gender":2,"id":19266,"job":"Writer","name":"Larry Cohen","profile_path":"/5p1y0KKAVv5EK2XAfs9hsIMDiBq.jpg"},{"credit_id":"575887cec3a3680af3000290","department":"Production","gender":2,"id":1591020,"job":"Producer","name":"Carter DeHaven","profile_path":null},{"credit_id":"557b269a9251414f2a000021","department":"Production","gender":2,"id":2721,"job":"Executive Producer","name":"John Daly","profile_path":"/aSn9EdjxbU5VkmF7INPdumGfJWG.jpg"},{"credit_id":"557b26b1c3a3683e8e00002a","department":"Production","gender":2,"id":2720,"job":"Executive Producer","name":"Derek Gibson","profile_path":null},{"credit_id":"557b26ddc3a3683e9500002b","department":"Art","gender":0,"id":6921,"job":"Production Design","name":"Gene Rudolf","profile_path":null},{"credit_id":"557b26ebc3a3683e91000032","department":"Art","gender":0,"id":1476550,"job":"Art Direction","name":"Robert Howland","profile_path":null},{"credit_id":"57c73b32c3a3680b29004d53","department":"Sound","gender":2,"id":75002,"job":"Music Supervisor","name":"Budd Carr","profile_path":null},{"credit_id":"57c73b999251417387006861","department":"Crew","gender":0,"id":1672752,"job":"Transportation Coordinator","name":"Fritz Braden","profile_path":null},{"credit_id":"57c73ba99251412f9b00850a","department":"Camera","gender":1,"id":589974,"job":"Still Photographer","name":"Lorey Sebastian","profile_path":null},{"credit_id":"57c73bc6c3a368555a00051b","department":"Camera","gender":0,"id":62023,"job":"Camera Operator","name":"Christopher Tufty","profile_path":null},{"credit_id":"57c73bdcc3a368556a000659","department":"Art","gender":2,"id":21616,"job":"Set Decoration","name":"Chris Butler","profile_path":null},{"credit_id":"57c7404fc3a3680ba40053e7","department":"Directing","gender":1,"id":1546213,"job":"Script Supervisor","name":"Marilyn Bailey","profile_path":null},{"credit_id":"57c74078c3a3680b290050b3","department":"Sound","gender":0,"id":1549652,"job":"Music Editor","name":"Allan K. Rosen","profile_path":null},{"credit_id":"57c7409bc3a3683e3e00b81f","department":"Sound","gender":2,"id":1378169,"job":"Sound Re-Recording Mixer","name":"Rick Kline","profile_path":null},{"credit_id":"57c740a79251417387006b50","department":"Sound","gender":2,"id":1378170,"job":"Sound Re-Recording Mixer","name":"Donald O. Mitchell","profile_path":null},{"credit_id":"57c740b692514154280008d3","department":"Sound","gender":2,"id":1378171,"job":"Sound Re-Recording Mixer","name":"Kevin O'Connell","profile_path":null},{"credit_id":"57c7411bc3a3685515000878","department":"Sound","gender":2,"id":1562803,"job":"Supervising Sound Editor","name":"Bill Phillips","profile_path":null},{"credit_id":"57c74155c3a3680ba400548e","department":"Sound","gender":0,"id":1672763,"job":"Production Sound Mixer","name":"Lee Alexander","profile_path":null}]}