{"id":5642,"cast":[{"cast_id":6,"character":"Eve","credit_id":"52fe4414c3a36847f80811a1","gender":1,"id":4680,"name":"Eve Meyer","order":0,"profile_path":"/wXIzCHodJ97p3tmp60RJxb4V1Ds.jpg"},{"cast_id":7,"character":"The Handyman","credit_id":"52fe4414c3a36847f80811a5","gender":2,"id":43876,"name":"Anthony-James Ryan","order":1,"profile_path":null},{"cast_id":8,"character":"Street sweeper","credit_id":"52fe4414c3a36847f80811a9","gender":0,"id":44535,"name":"Frank Bolger","order":2,"profile_path":null},{"cast_id":9,"character":"Girl","credit_id":"52fe4414c3a36847f80811ad","gender":0,"id":44536,"name":"Iris Bristol","order":3,"profile_path":null},{"cast_id":10,"character":"o.A.","credit_id":"52fe4414c3a36847f80811b1","gender":0,"id":44537,"name":"Joseph Carroll","order":4,"profile_path":null},{"cast_id":11,"character":"Girl","credit_id":"52fe4414c3a36847f80811b5","gender":0,"id":44538,"name":"Rita Day","order":5,"profile_path":null},{"cast_id":12,"character":"Artist","credit_id":"52fe4414c3a36847f80811b9","gender":0,"id":44539,"name":"James A. Evanoff","order":6,"profile_path":null},{"cast_id":13,"character":"Girl","credit_id":"52fe4414c3a36847f80811bd","gender":0,"id":44540,"name":"Gigi Frost","order":7,"profile_path":null},{"cast_id":14,"character":"Girl","credit_id":"52fe4414c3a36847f80811c1","gender":0,"id":44541,"name":"Mildred Knezevich","order":8,"profile_path":null},{"cast_id":15,"character":"Francesca","credit_id":"52fe4414c3a36847f80811c5","gender":0,"id":44542,"name":"Francesca Leslie","order":9,"profile_path":null},{"cast_id":16,"character":"Narrator","credit_id":"52fe4414c3a36847f80811c9","gender":0,"id":44543,"name":"Lee Merrin","order":10,"profile_path":null}],"crew":[{"credit_id":"52fe4414c3a36847f8081185","department":"Directing","gender":2,"id":4590,"job":"Director","name":"Russ Meyer","profile_path":"/4w6izR5bsjPNTQufl69K7qodcIb.jpg"},{"credit_id":"52fe4414c3a36847f808118b","department":"Writing","gender":2,"id":4590,"job":"Screenplay","name":"Russ Meyer","profile_path":"/4w6izR5bsjPNTQufl69K7qodcIb.jpg"},{"credit_id":"52fe4414c3a36847f8081191","department":"Production","gender":2,"id":4590,"job":"Producer","name":"Russ Meyer","profile_path":"/4w6izR5bsjPNTQufl69K7qodcIb.jpg"},{"credit_id":"52fe4414c3a36847f8081197","department":"Camera","gender":2,"id":4590,"job":"Director of Photography","name":"Russ Meyer","profile_path":"/4w6izR5bsjPNTQufl69K7qodcIb.jpg"},{"credit_id":"52fe4414c3a36847f808119d","department":"Editing","gender":2,"id":4590,"job":"Editor","name":"Russ Meyer","profile_path":"/4w6izR5bsjPNTQufl69K7qodcIb.jpg"}]}