{"adult":false,"backdrop_path":"/3DW3xHM7FgdE8XzpODbEfvlR9qR.jpg","belongs_to_collection":null,"budget":0,"genres":[{"id":18,"name":"Drama"},{"id":10749,"name":"Romance"}],"homepage":null,"id":899,"imdb_id":"tt0009968","original_language":"en","original_title":"Broken Blossoms","overview":"The love story of an abused English girl and a Chinese Buddhist in a time when London was a brutal and harsh place to live.","popularity":5.848,"poster_path":"/sr5yZl89NOtkXiZEyvNx5uz9JvB.jpg","production_companies":[{"id":4759,"logo_path":null,"name":"D.W. Griffith Productions","origin_country":"US"}],"production_countries":[{"iso_3166_1":"US","name":"United States of America"}],"release_date":"1919-05-13","revenue":0,"runtime":89,"spoken_languages":[{"iso_639_1":"xx","name":"No Language"}],"status":"Released","tagline":"","title":"Broken Blossoms","video":false,"vote_average":7.1,"vote_count":80}