{"adult":false,"backdrop_path":"/d9UBz6c39l5tTSC0Dwjg5HrdrwN.jpg","belongs_to_collection":null,"budget":0,"genres":[{"id":35,"name":"Comedy"},{"id":18,"name":"Drama"},{"id":10749,"name":"Romance"}],"homepage":null,"id":9089,"imdb_id":"tt0113321","original_language":"en","original_title":"Home for the Holidays","overview":"After losing her job, making out with her soon to be ex-boss, and finding out that her daughter plans to spend Thanksgiving with her boyfriend, Claudia Larson has to face spending the holiday with her family. She wonders if she can survive their crazy antics.","popularity":7.805,"poster_path":"/a8MslR6deQQVe8JR542XDSwHiPB.jpg","production_companies":[{"id":802,"logo_path":null,"name":"Egg Pictures","origin_country":""},{"id":4,"logo_path":"/fycMZt242LVjagMByZOLUGbCvv3.png","name":"Paramount","origin_country":"US"},{"id":1382,"logo_path":"/sOg7LGESPH5vCTOIdbMhLuypoLL.png","name":"PolyGram Filmed Entertainment","origin_country":"US"}],"production_countries":[{"iso_3166_1":"US","name":"United States of America"}],"release_date":"1995-11-02","revenue":17519169,"runtime":103,"spoken_languages":[{"iso_639_1":"en","name":"English"}],"status":"Released","tagline":"We'll do it every year... until we get it right.","title":"Home for the Holidays","video":false,"vote_average":6.3,"vote_count":77}